gmctl/__init__.py
gmctl/commit.py
gmctl/db_functions.py
gmctl/ecs_deployment.py
gmctl/gmclient.py
gmctl/gmctl.py
gmctl/k8s_deployment.py
gmctl/lambda_deployment.py
gmctl/repository.py
gmctl/riskiq.py
gmctl/utils.py
gmctl-0.9.0.dist-info/METADATA
gmctl-0.9.0.dist-info/WHEEL
gmctl-0.9.0.dist-info/entry_points.txt
gmctl-0.9.0.dist-info/top_level.txt
gmctl-0.9.0.dist-info/RECORD
