Metadata-Version: 2.4
Name: gmctl
Version: 0.9.0
Requires-Dist: python-dotenv
Requires-Dist: Click
Requires-Dist: pydantic
Requires-Dist: requests
Requires-Dist: tabulate
Dynamic: requires-dist
